duckberg/__about__.py
duckberg/__init__.py
duckberg/exceptions.py
duckberg/sqlparser.py
duckberg/table.py
duckberg-0.3.1.dist-info/METADATA
duckberg-0.3.1.dist-info/WHEEL
duckberg-0.3.1.dist-info/licenses/LICENSE.txt
duckberg-0.3.1.dist-info/RECORD
