Metadata-Version: 2.1
Name: duckberg
Version: 0.3.1
Project-URL: Documentation, https://github.com/slidoapp/duckberg/blob/main/README.md
Project-URL: Issues, https://github.com/slidoapp/duckberg/issues
Project-URL: Source, https://github.com/slidoapp/duckberg
Author-email: gregor <gkaretka@cisco.com>, jojo <jcechovs@cisco.com>
License-Expression: Apache-2.0
License-File: LICENSE.txt
Classifier: Programming Language :: Python :: 3.10
Requires-Python: >=3.10
Requires-Dist: duckdb==0.9.2
Requires-Dist: pandas==2.2.0
Requires-Dist: pyiceberg[glue,s3fs]==0.5.1
Requires-Dist: sqlparse==0.4.4
